MANIFEST.in
README.rst
setup.py
feature_selection_fdr/__init__.py
feature_selection_fdr/barber_candes_selection.py
feature_selection_fdr/filter.py
feature_selection_fdr/forward_selection.py
feature_selection_fdr/knockoff_features_construction.py
feature_selection_fdr/models.py
feature_selection_fdr/utils.py
feature_selection_fdr/varimp.py
feature_selection_fdr.egg-info/PKG-INFO
feature_selection_fdr.egg-info/SOURCES.txt
feature_selection_fdr.egg-info/dependency_links.txt
feature_selection_fdr.egg-info/not-zip-safe
feature_selection_fdr.egg-info/requires.txt
feature_selection_fdr.egg-info/top_level.txt
tests/DSS_classification.py
tests/DSS_regression.py
tests/__init__.py
tests/knockoff_classification.py
tests/knockoff_regression.py
tests/no_model_selection.py
tests/test_barber_candes_selection.py