Metadata-Version: 1.1
Name: feature-selection-fdr
Version: 0.1
Summary: Feature selection with FDR control.
Home-page: https://github.com/mehdirostami/feature_selection_fdr
Author: Mehdi Rostami
Author-email: mehdi.rostamiforooshani@mail.utoronto.ca
License: UNKNOWN
Platform: UNKNOWN
Classifier: Development Status :: 3 - Alpha
Classifier: License :: OSI Approved :: MIT License
Classifier: Programming Language :: Python :: 2.7
